Metadata-Version: 1.0
Name: newspeak
Version: 0.1
Summary: Standalone Django based feed aggregator.
Home-page: http://github.com/bitsoffreedom/newspeak/
Author: Mathijs de Bruin
Author-email: mathijs@visualspace.nl
License: UNKNOWN
Platform: UNKNOWN
Classifier: Development Status :: 4 - Beta
Classifier: Environment :: Web Environment
Classifier: Framework :: Django
Classifier: Intended Audience :: Developers
Classifier: License :: OSI Approved :: BSD License
Classifier: Operating System :: OS Independent
Classifier: Programming Language :: Python
Classifier: Topic :: Utilities
